ailoganalyzer/__init__.py
ailoganalyzer/dataset/__init__.py
ailoganalyzer/dataset/dataset.py
ailoganalyzer/dataset/dbm_vec.py
ailoganalyzer/dataset/template_miner.py
ailoganalyzer/dataset/utils_semantic_vec.py
ailoganalyzer/model/LSTM.py
ailoganalyzer/model/__init__.py
ailoganalyzer-1.0.0.dist-info/LICENSE
ailoganalyzer-1.0.0.dist-info/METADATA
ailoganalyzer-1.0.0.dist-info/WHEEL
ailoganalyzer-1.0.0.dist-info/top_level.txt
ailoganalyzer-1.0.0.dist-info/RECORD
