Metadata-Version: 2.1
Name: ailoganalyzer
Version: 1.0.0
Summary: AI-Log-Analyzer is an open source toolkit, user friendly, based on deep-learning, for unstructured log anomaly detection.
Author: Léo DECHAUMET
License: GNU GENERAL PUBLIC LICENSE
Project-URL: Homepage, https://github.com/ixalodecte/AI-Log-Analyzer
Keywords: log,NLP,anomaly detection
Classifier: Development Status :: 3 - Alpha
Classifier: License :: OSI Approved :: GNU General Public License v3 (GPLv3)
Classifier: Programming Language :: Python :: 3
Classifier: Programming Language :: Python :: 3.8
Classifier: Programming Language :: Python :: 3.9
Classifier: Programming Language :: Python :: 3.10
Classifier: Programming Language :: Python :: 3.11
Classifier: Programming Language :: Python :: 3.12
Classifier: Programming Language :: Python :: 3.13
Classifier: Programming Language :: Python :: 3.14
Classifier: Topic :: Internet :: Log Analysis
Classifier: Topic :: Scientific/Engineering :: Artificial Intelligence
Requires-Python: >=3.8
License-File: LICENSE
Requires-Dist: drain3
Requires-Dist: spacy
Requires-Dist: lightning
